pytest_tno/tno/mpc/communication/__init__.py
pytest_tno/tno/mpc/communication/py.typed
pytest_tno/tno/mpc/communication/pytest_pool_fixtures.py
pytest_tno/tno/mpc/communication/pytest_pool_http_fixtures.py
pytest_tno/tno/mpc/communication/pytest_pool_mock_fixtures.py
pytest_tno/tno/mpc/communication/utils.py
tno/mpc/communication/__init__.py
tno/mpc/communication/buffer.py
tno/mpc/communication/exceptions.py
tno/mpc/communication/functions.py
tno/mpc/communication/pool.py
tno/mpc/communication/py.typed
tno/mpc/communication/communicators/__init__.py
tno/mpc/communication/communicators/communicator.py
tno/mpc/communication/communicators/http_communicator.py
tno/mpc/communication/communicators/mock_communicator.py
tno/mpc/communication/packers/__init__.py
tno/mpc/communication/packers/packer.py
tno/mpc/communication/packers/serialization.py
tno/mpc/communication/serializer_plugins/__init__.py
tno/mpc/communication/serializer_plugins/_register.py
tno/mpc/communication/serializer_plugins/bitarray.py
tno/mpc/communication/serializer_plugins/gmpy.py
tno/mpc/communication/serializer_plugins/int.py
tno/mpc/communication/serializer_plugins/numpy.py
tno/mpc/communication/serializer_plugins/pandas.py
tno/mpc/communication/serializer_plugins/torch.py
tno/mpc/communication/serializer_plugins/tuple.py
tno/mpc/communication/test/__init__.py
tno/mpc/communication/test/conftest.py
tno/mpc/communication/test/test_integration_pool_2p.py
tno/mpc/communication/test/test_integration_pool_3p.py
tno/mpc/communication/test/test_pool.py
tno/mpc/communication/test/test_pool_https_2p.py
tno/mpc/communication/test/util.py
tno/mpc/communication/test/communicators/__init__.py
tno/mpc/communication/test/communicators/test_communicator.py
tno/mpc/communication/test/serializer_plugins/__init__.py
tno/mpc/communication/test/serializer_plugins/test_packing.py
tno/mpc/communication/test/serializer_plugins/test_packing_gmpy.py
tno/mpc/communication/test/tls_certs/README.md
tno_mpc_communication-5.0.4.dist-info/licenses/LICENSE
tno_mpc_communication-5.0.4.dist-info/METADATA
tno_mpc_communication-5.0.4.dist-info/WHEEL
tno_mpc_communication-5.0.4.dist-info/entry_points.txt
tno_mpc_communication-5.0.4.dist-info/top_level.txt
tno_mpc_communication-5.0.4.dist-info/RECORD
