Metadata-Version: 2.4
Name: tno.mpc.communication
Version: 5.0.4
Summary: MPC Communication module
Author-email: TNO PET Lab <petlab@tno.nl>
Maintainer-email: TNO PET Lab <petlab@tno.nl>
License: Apache License, Version 2.0
Project-URL: Homepage, https://pet.tno.nl/
Project-URL: Documentation, https://docs.pet.tno.nl/mpc/communication/5.0.4
Project-URL: Source, https://github.com/TNO-MPC/communication
Keywords: TNO,MPC,multi-party computation,communication
Platform: any
Classifier: License :: OSI Approved :: Apache Software License
Classifier: Programming Language :: Python :: 3
Classifier: Operating System :: OS Independent
Classifier: Intended Audience :: Developers
Classifier: Intended Audience :: Information Technology
Classifier: Intended Audience :: Science/Research
Classifier: Typing :: Typed
Classifier: Topic :: Security :: Cryptography
Requires-Python: >=3.9
License-File: LICENSE
Requires-Dist: aiohttp<4.0,>=3.6.1
Requires-Dist: ormsgpack>=1.1.0
Requires-Dist: tenacity>=8.0.0
Requires-Dist: typing_extensions~=4.5; python_version < "3.12"
Provides-Extra: gmpy
Requires-Dist: tno.mpc.encryption_schemes.utils[gmpy]; extra == "gmpy"
Provides-Extra: bitarray
Requires-Dist: bitarray; extra == "bitarray"
Provides-Extra: numpy
Requires-Dist: numpy; extra == "numpy"
Provides-Extra: pandas
Requires-Dist: pandas; extra == "pandas"
Requires-Dist: pyarrow; extra == "pandas"
Requires-Dist: packaging; extra == "pandas"
Provides-Extra: pytest
Requires-Dist: aiocache~=0.12; extra == "pytest"
Requires-Dist: pytest-asyncio~=1.0; extra == "pytest"
Provides-Extra: tls
Requires-Dist: pyOpenSSL; extra == "tls"
Provides-Extra: torch
Requires-Dist: safetensors[torch]~=0.4; extra == "torch"
Provides-Extra: tests
Requires-Dist: tno.mpc.communication[bitarray,gmpy,numpy,pandas,pytest,tls,torch]; extra == "tests"
Requires-Dist: mypy_extensions; extra == "tests"
Requires-Dist: pandas-stubs; extra == "tests"
Requires-Dist: pytest~=8.0; extra == "tests"
Requires-Dist: pytest-timeout~=2.2; extra == "tests"
Requires-Dist: typeguard; extra == "tests"
Dynamic: license-file
